[
  {
    "id": 1,
    "type": "content",
    "label": "Prop 1",
    "block_id": null,
    "reference_id": null
  },
  {
    "id": 2,
    "type": "reference",
    "label": "Prop 2",
    "block_id": 1,
    "reference_id": null
  },
  {
    "id": 3,
    "type": "meta",
    "label": "Prop 3",
    "block_id": 1,
    "reference_id": null
  },
  {
    "id": 4,
    "type": "content",
    "label": "Prop 4",
    "block_id": 2,
    "reference_id": null
  },
  {
    "id": 5,
    "type": "action",
    "label": "Action 5",
    "block_id": 2,
    "reference_id": null
  }
]